telecomlib/__init__.py
telecomlib/getip/__init__.py
telecomlib/getip/getip.py
telecomlib/shell/__init__.py
telecomlib/shell/usage.py
telecomlib/star/__init__.py
telelib/__init__.py
telelib/ip_tools/__init__.py
telelib/ip_tools/getip.py
telelib/shell/__init__.py
telelib/shell/usage.py
telelib/star/__init__.py
telecomlib-0.0.2.dist-info/LICENSE
telecomlib-0.0.2.dist-info/METADATA
telecomlib-0.0.2.dist-info/WHEEL
telecomlib-0.0.2.dist-info/entry_points.txt
telecomlib-0.0.2.dist-info/top_level.txt
telecomlib-0.0.2.dist-info/zip-safe
telecomlib-0.0.2.dist-info/RECORD
